README.rst
setup.py
eda/__init__.py
eda/dto.py
eda/exc.py
eda.egg-info/PKG-INFO
eda.egg-info/SOURCES.txt
eda.egg-info/dependency_links.txt
eda.egg-info/not-zip-safe
eda.egg-info/requires.txt
eda.egg-info/top_level.txt
eda/bus/__init__.py
eda/bus/imessagebus.py
eda/event/__init__.py
eda/event/base.py
eda/event/handler.py