Metadata-Version: 1.1
Name: eda
Version: 1.0.0alpha5
Summary: A Python framework for event-driven architectures.
Home-page: https://www.sousouindustries.com/
Author: Cochise Ruhulessin
Author-email: cochise.ruhulessin@sousouindustries.com
License: UNKNOWN
Platform: UNKNOWN
Classifier: Development Status :: 2 - Pre-Alpha
Classifier: Environment :: Web Environment
Classifier: Programming Language :: Python
Classifier: Programming Language :: Python :: 3
Classifier: Programming Language :: Python :: 3.4
Classifier: Programming Language :: Python :: 3.5
Classifier: Topic :: Software Development :: Libraries :: Python Modules
